<?xml version="1.0" encoding="utf-8" ?>
<c2eventsheet>
    <!--All the 'name' attributes are ignored by Construct 2 - they are there for readability only.-->
    <name>e_plot</name>
    <events>
        <include>e_fadeInOut</include>
        <event-block sid="687401531275549">
            <conditions>
                <condition id="-2" name="On start of layout" sid="566273638513254" type="System" />
            </conditions>
            <actions>
                <action id="-2" name="Go to layout" sid="285620358542761" type="System">
                    <param id="0" name="Layout">game</param>
                </action>
            </actions>
        </event-block>
    </events>
</c2eventsheet>
